keyso/__init__.py
keyso/grammar.py
keyso/metadata.py
keyso-0.1.1.dist-info/METADATA
keyso-0.1.1.dist-info/WHEEL
keyso-0.1.1.dist-info/entry_points.txt
keyso-0.1.1.dist-info/RECORD
