Metadata-Version: 2.1
Name: keyso
Version: 0.1.1
Summary: A Set Algebra for Key-Value Pairs
Project-URL: Documentation, https://gitlab.com/ambhora/software/keyso
Project-URL: Issues, https://gitlab.com/ambhora/software/keyso/issues
Project-URL: Source, https://gitlab.com/ambhora/software/keyso
Author-email: Jayesh Badwaik <j.badwaik@fz-juelich.de>
License-Expression: Apache-2.0
